<?xml version="1.0"?>
<!DOCTYPE hibernate-mapping PUBLIC "-//Hibernate/Hibernate Mapping DTD 3.0//EN"
"http://hibernate.sourceforge.net/hibernate-mapping-3.0.dtd">

<hibernate-mapping>
	<class name="model.Friend" table="friend">
		<id name="user_id" type="int">
			<column name="user_id" />
			<generator class="assigned" />
		</id>
		<property name="friend_id" type="int">
			<column name="friend_id" />
		</property>
		<property name="isFriend" type="int">
			<column name="isFriend" />
		</property>

	</class>
</hibernate-mapping>
